pyeqx/encryption/__init__.py
pyeqx/encryption/cli.py
pyeqx/encryption/cli_kyber512.py
pyeqx/encryption/cli_pgp.py
pyeqx/encryption/kyber512.py
pyeqx/encryption/pgp.py
pyeqx/encryption/utils.py
pyeqx_encryption-0.2.0.dist-info/METADATA
pyeqx_encryption-0.2.0.dist-info/WHEEL
pyeqx_encryption-0.2.0.dist-info/entry_points.txt
pyeqx_encryption-0.2.0.dist-info/top_level.txt
pyeqx_encryption-0.2.0.dist-info/RECORD
